tool/Tool.py
tool/__init__.py
rkt_tool_lib-1.4.1.dist-info/LICENSE
rkt_tool_lib-1.4.1.dist-info/METADATA
rkt_tool_lib-1.4.1.dist-info/WHEEL
rkt_tool_lib-1.4.1.dist-info/top_level.txt
rkt_tool_lib-1.4.1.dist-info/RECORD
