Metadata-Version: 2.1
Name: rkt-tool-lib
Version: 1.4.1
Summary: RootKit custom tool Lib
Author: RootKit
Author-email: rootkit@rootkit-lab.org
Classifier: Development Status :: 5 - Production/Stable
Classifier: Intended Audience :: Developers
Classifier: Intended Audience :: End Users/Desktop
Classifier: Intended Audience :: Information Technology
Classifier: License :: OSI Approved :: MIT License
Classifier: Natural Language :: English
Classifier: Natural Language :: French
Classifier: Operating System :: OS Independent
Classifier: Programming Language :: Python :: 3.7
Classifier: Topic :: Utilities
Requires-Python: >=3.7
License-File: LICENSE
